airbyte_source_datadog_usage/__init__.py
airbyte_source_datadog_usage/run.py
airbyte_source_datadog_usage/schemas/estimated_cost.json
airbyte_source_datadog_usage/schemas/hourly_usage_by_products.json
airbyte_source_datadog_usage/source.py
airbyte_source_datadog_usage/spec.yaml
main.py
airbyte_source_datadog_usage-0.2.5.dist-info/METADATA
airbyte_source_datadog_usage-0.2.5.dist-info/WHEEL
airbyte_source_datadog_usage-0.2.5.dist-info/entry_points.txt
airbyte_source_datadog_usage-0.2.5.dist-info/RECORD
